ethgas/__init__.py
ethgas/rest/__init__.py
ethgas/rest/api_client.py
ethgas/rest/api_constants.py
ethgas/utils/__init__.py
ethgas/utils/constants.py
ethgas/utils/exceptions.py
ethgas/utils/helper.py
ethgas/websocket/__init__.py
ethgas/websocket/ws_client.py
ethgas/websocket/ws_constants.py
python_ethgas-0.3.0.dist-info/LICENSE
python_ethgas-0.3.0.dist-info/METADATA
python_ethgas-0.3.0.dist-info/WHEEL
python_ethgas-0.3.0.dist-info/top_level.txt
python_ethgas-0.3.0.dist-info/RECORD
