Metadata-Version: 2.2
Name: python-ethgas
Version: 0.3.0
Summary: Unofficial EthGas client packages
Author-email: gaspy503 <gaspy503@gmail.com>
Project-URL: Homepage, https://github.com/gaspy503/python-ethgas
Project-URL: Bug Tracker, https://github.com/gaspy503/python-ethgas/issues
Classifier: Programming Language :: Python :: 3
Classifier: License :: OSI Approved :: MIT License
Classifier: Operating System :: OS Independent
License-File: LICENSE
Requires-Dist: requests~=2.32.0
Requires-Dist: eth-account>=0.13.1
Requires-Dist: urllib3~=2.2.2
Requires-Dist: web3~=7.4.0
Requires-Dist: python-dotenv~=0.21.0
Requires-Dist: websocket-client~=1.6.4
